dibs_daten/__init__.py
dibs_daten/data_utils.py
dibs_daten/data/__init__.py
dibs_daten/data/LCA/Primary_energy_and_emission_factors.csv
dibs_daten/data/LCA/Primary_energy_and_emission_factors.xlsx
dibs_daten/data/auxiliary/TEKs/TEK_NWG_Vergleichswerte.csv
dibs_daten/data/auxiliary/TEKs/TEK_NWG_Vergleichswerte.xlsx
dibs_daten/data/auxiliary/TEKs/TEK_NWG_Vergleichswerte_zuweisung.csv
dibs_daten/data/auxiliary/norm_profiles/profiles_DIN18599_SIA2024.xlsx
dibs_daten/data/auxiliary/norm_profiles/profiles_zuweisungen.csv
dibs_daten/data/auxiliary/occupancy_schedules/Ausstellungshalle.csv
dibs_daten/data/auxiliary/occupancy_schedules/Behandlungsraum.csv
dibs_daten/data/auxiliary/occupancy_schedules/Bibliothek.csv
dibs_daten/data/auxiliary/occupancy_schedules/Bueros_SchalterhalleEmpfang.csv
dibs_daten/data/auxiliary/occupancy_schedules/Fachgeschaeft.csv
dibs_daten/data/auxiliary/occupancy_schedules/Fitnessraum_Schwimmhalle.csv
dibs_daten/data/auxiliary/occupancy_schedules/GarderobeDusche.csv
dibs_daten/data/auxiliary/occupancy_schedules/Hotelzimmer.csv
dibs_daten/data/auxiliary/occupancy_schedules/KrankenhausMix.csv
dibs_daten/data/auxiliary/occupancy_schedules/KuecheTeekueche.csv
dibs_daten/data/auxiliary/occupancy_schedules/Laborraum.csv
dibs_daten/data/auxiliary/occupancy_schedules/Lagerhalle.csv
dibs_daten/data/auxiliary/occupancy_schedules/Lebensmittelverkauf.csv
dibs_daten/data/auxiliary/occupancy_schedules/Mehrzweckhalle.csv
dibs_daten/data/auxiliary/occupancy_schedules/Parkhaus.csv
dibs_daten/data/auxiliary/occupancy_schedules/ProduktionGrob.csv
dibs_daten/data/auxiliary/occupancy_schedules/References.txt
dibs_daten/data/auxiliary/occupancy_schedules/Restaurant.csv
dibs_daten/data/auxiliary/occupancy_schedules/Schulzimmer_Hoersaal.csv
dibs_daten/data/auxiliary/occupancy_schedules/Selbstbedienungsrestaurant.csv
dibs_daten/data/auxiliary/occupancy_schedules/Serverraum.csv
dibs_daten/data/auxiliary/occupancy_schedules/Stationszimmer.csv
dibs_daten-1.0.0.dist-info/LICENSE
dibs_daten-1.0.0.dist-info/WHEEL
dibs_daten-1.0.0.dist-info/METADATA
dibs_daten-1.0.0.dist-info/RECORD
